asyncvnc2.py
asyncvnc2-2.0.0.dist-info/LICENSE
asyncvnc2-2.0.0.dist-info/METADATA
asyncvnc2-2.0.0.dist-info/WHEEL
asyncvnc2-2.0.0.dist-info/top_level.txt
asyncvnc2-2.0.0.dist-info/RECORD
