Metadata-Version: 2.2
Name: asyncvnc2
Version: 2.0.0
Summary: Asynchronous VNC for Python v2
Home-page: https://github.com/andrews239/asyncvnc2
Author: Andrew Shirayev
License: GPL
Requires-Python: >=3.7
License-File: LICENSE
Requires-Dist: cryptography
Requires-Dist: keysymdef
Requires-Dist: numpy
